{
    "header": {
        "type": "AMNESTY HEARINGS",
        "starting date": "1999-08-11",
        "location": "DURBAN",
        "day": "2",
        "names": [
            "LAWRENCE GERALD WASSERMAN"
        ],
        "case number": "AM4508/96",
        "url": "http://sabctrc.saha.org.za/hearing.php?id=53605&t=&tab=hearings",
        "original file": "http://sabctrc.saha.org.za/originals/amntrans/1999/9908100903_dbn_990811db.htm",
        "speakers": [
            "MR VISSER",
            "CHAIRPERSON",
            "MS THABETHE",
            "LAWRENCE GERALD WASSERMAN",
            "MR NEL",
            "MR LAX",
            "ADV BOSMAN"
        ],
        "original_speakers": [
            "MR VISSER",
            "CHAIRPERSON",
            "MS THABETHE",
            "LAWRENCE GERALD WASSERMAN",
            "MR WASSERMAN",
            "MR NEL",
            "MR LAX",
            "ADV BOSMAN"
        ]
    },
    "testimony": [
        [
            "MR VISSER",
            "Chairperson, the last applicant for whom we appear is W/O Lawrence Gerald Wasserman, whom we call to the stand.  He will give his evidence in English.  We beg leave to hand up to you a summary of his evidence and we would propose that that be marked Exhibit F.",
            "Male"
        ],
        [
            "CHAIRPERSON",
            "That will be so marked.",
            "Unknown"
        ],
        [
            "MS THABETHE",
            "Thank you, Mr Chairman.  He has no objection to taking the prescribed oath.",
            "Female"
        ],
        [
            "LAWRENCE GERALD WASSERMAN",
            "(sworn states)",
            "Unknown"
        ],
        [
            "MR VISSER",
            "Please take a seat, Mr Wasserman.  You're an applicant in this incident, is that correct?",
            "Male"
        ],
        [
            "LAWRENCE GERALD WASSERMAN",
            "That's correct, Mr Chairman.",
            "Male"
        ],
        [
            "MR VISSER",
            "Have you perused Exhibit A?",
            "Male"
        ],
        [
            "LAWRENCE GERALD WASSERMAN",
            "That's correct, Mr Chairman.",
            "Male"
        ],
        [
            "MR VISSER",
            "And do you find yourself in agreement or disagreement with the contents of Exhibit A?",
            "Male"
        ],
        [
            "LAWRENCE GERALD WASSERMAN",
            "I concur with the contents.",
            "Male"
        ],
        [
            "MR VISSER",
            "And you ask that that be incorporated in your evidence, together with references to other evidence which Exhibit A contains, is that correct?",
            "Male"
        ],
        [
            "LAWRENCE GERALD WASSERMAN",
            "Correct, Mr Chairman.",
            "Male"
        ],
        [
            "MR VISSER",
            "You have previously given evidence before another Amnesty Committee in the application with regard to Ndwandwe, the KwaMashu 3, and Pumezo Ncgweni, is that correct?",
            "Male"
        ],
        [
            "LAWRENCE GERALD WASSERMAN",
            "Correct, Mr Chairman.",
            "Male"
        ],
        [
            "MR VISSER",
            "If you will please turn to page 2, and will you inform the Committee what your knowledge and participation was in the present incident.  You first of all refer to the evidence of Col Vorster.  You have also heard the evidence of Col Botha this morning, in regard to the background of the violence in Natal and the situation in Swaziland, is that correct?",
            "Male"
        ],
        [
            "LAWRENCE GERALD WASSERMAN",
            "That's correct, Mr Chairman.",
            "Male"
        ],
        [
            "MR VISSER",
            "Do you also find yourself in agreement with that?",
            "Male"
        ],
        [
            "LAWRENCE GERALD WASSERMAN",
            "I do.",
            "Male"
        ],
        [
            "MR VISSER",
            "Would you please continue at page 2, paragraph 2, of Exhibit F.",
            "Male"
        ],
        [
            "LAWRENCE GERALD WASSERMAN",
            "Yes, Mr Chairman.\n\"I was instructed by Col Botha from Durban, to accompany him on an operation to Swaziland.  I was informed by him that there was information to hand that an important Umkhonto weSizwe member, Dion Cele, had indicated that he would be willing to work for the Security Branch.  And our mission would be to abduct Dion Cele from Swaziland, bring him to the RSA and attempt to turn him and recruit him and place him back.\"",
            "Male"
        ],
        [
            "MR VISSER",
            "Right.  What did you know about Cele, what were you told?\nMR WASSERMAN\n\"We knew that Dion Cele was a member of border work, attached to the Natal machinery.  He lived in Manzini and he was undergoing night school at Scot, at a technical college in Manzini in Swaziland.\n\t\tAnd as a border worker he was responsible for the infiltration of MK into Natal and the subsequent movement of weapons with those units and responsible for acts of terror within this province.\"",
            "Male"
        ],
        [
            "CHAIRPERSON",
            "Yes, do carry on.\nMR WASSERMAN\n\"I was informed that there was an informer who was handled by Mr Vorster ...\"\n...(intervention)",
            "Unknown"
        ],
        [
            "MR VISSER",
            "Goodwill Sikhakane?",
            "Male"
        ],
        [
            "LAWRENCE GERALD WASSERMAN",
            "Goodwill Sikhakane.  I learnt the name at a later stage.\n\"... and he would assist in bringing forward Dion Cele.\"",
            "Male"
        ],
        [
            "MR VISSER",
            "Right.  You travelled with Botha from Durban in a kombi, is that correct, to Amsterdam?",
            "Male"
        ],
        [
            "LAWRENCE GERALD WASSERMAN",
            "That is correct, Mr Chairman.",
            "Male"
        ],
        [
            "MR VISSER",
            "Did you go in with Botha and Vorster on the reconnaissance trip?",
            "Male"
        ],
        [
            "LAWRENCE GERALD WASSERMAN",
            "No, Mr Chairman.",
            "Male"
        ],
        [
            "MR VISSER",
            "Before the abduction was performed?",
            "Male"
        ],
        [
            "LAWRENCE GERALD WASSERMAN",
            "No.",
            "Male"
        ],
        [
            "MR VISSER",
            "Right.  Did you stay behind in Amsterdam?",
            "Male"
        ],
        [
            "LAWRENCE GERALD WASSERMAN",
            "That is correct, Mr Chairman.",
            "Male"
        ],
        [
            "MR VISSER",
            "Alright.  And then on the next occasion when Swaziland was entered, did you then accompany them?",
            "Male"
        ],
        [
            "LAWRENCE GERALD WASSERMAN",
            "That's correct, Mr Chairman.",
            "Male"
        ],
        [
            "MR VISSER",
            "Can you just tell us about that?\nMR WASSERMAN\n\"Col Botha and I took the kombi in.  We entered legally, proceeded to Manzini to the George Hotel and there linked up with Sikhakane.\"",
            "Male"
        ],
        [
            "MR VISSER",
            "Yes?",
            "Male"
        ],
        [
            "LAWRENCE GERALD WASSERMAN",
            "Form there ...(intervention)",
            "Male"
        ],
        [
            "MR VISSER",
            "Did he come, get into the kombi with you?",
            "Male"
        ],
        [
            "LAWRENCE GERALD WASSERMAN",
            "Yes, Mr Chairman.",
            "Male"
        ],
        [
            "MR VISSER",
            "And at one stage, was he asked to take over the driving of the kombi?",
            "Male"
        ],
        [
            "LAWRENCE GERALD WASSERMAN",
            "That's correct, Mr Chairman.\n\"He then drove to a spot near the main gates of the Scot, of the technical training college in Manzini.\"",
            "Male"
        ],
        [
            "MR VISSER",
            "And what did you do, where did you go?\nMR WASSERMAN\n\"I and Mr Botha then took up hiding places in the rear of the kombi and we were covered by some large cardboard boxes.\"",
            "Male"
        ],
        [
            "MR VISSER",
            "Yes.\nMR WASSERMAN\n\"Shortly after standing off outside there, Dion Cele came forward and he entered the vehicle by the sliding door.\"",
            "Male"
        ],
        [
            "MR VISSER",
            "Why not through the passenger door?",
            "Male"
        ],
        [
            "LAWRENCE GERALD WASSERMAN",
            "He couldn't enter through the left-hand door as we had jimmied that lock to make it useless, thereby enforcing him to use the sliding door, giving us the sign that he was indeed in the vehicle.",
            "Male"
        ],
        [
            "MR VISSER",
            "Alright.  Now I may have understood this incorrectly, judging from what Mr Botha says.  You say in paragraph 6\n\"He went to sit on the passenger's seat next to Sikhakane.\"\nIs that the position?",
            "Male"
        ],
        [
            "LAWRENCE GERALD WASSERMAN",
            "I think that is correct position, yes.",
            "Male"
        ],
        [
            "MR VISSER",
            "So I did understand you correctly.  You differ from Mr Botha, who says that he sat on the seat behind the driver.",
            "Male"
        ],
        [
            "LAWRENCE GERALD WASSERMAN",
            "I'm not too sure where he was.  I do realise - I then pulled him over once we had moved off.  Sikhakane drove off.  There was no indication from Cele that he was aware of our presence in the vehicle.  I then, and Col Botha, then moved the box and grabbed hold of Cele and pulled him over to where I was, to the rear of the vehicle.",
            "Male"
        ],
        [
            "MR VISSER",
            "What did he do?",
            "Male"
        ],
        [
            "LAWRENCE GERALD WASSERMAN",
            "He shouted and he kicked and he struggled.",
            "Male"
        ],
        [
            "MR VISSER",
            "Yes, what did you do?",
            "Male"
        ],
        [
            "LAWRENCE GERALD WASSERMAN",
            "I used force.  I smacked, I slapped him.",
            "Male"
        ],
        [
            "MR VISSER",
            "You say you slapped and punched him a few times.",
            "Male"
        ],
        [
            "LAWRENCE GERALD WASSERMAN",
            "Yes, that's correct.",
            "Male"
        ],
        [
            "MR VISSER",
            "Would that be correct?",
            "Male"
        ],
        [
            "LAWRENCE GERALD WASSERMAN",
            "And spoke and shouted at him.",
            "Male"
        ],
        [
            "MR VISSER",
            "Yes.",
            "Male"
        ],
        [
            "LAWRENCE GERALD WASSERMAN",
            "And afterwards he became quiet when he realised that - I had told him that we're policemen from South Africa, and upon that he relaxed, he then quietened down.",
            "Male"
        ],
        [
            "MR VISSER",
            "Well he became quiet.",
            "Male"
        ],
        [
            "LAWRENCE GERALD WASSERMAN",
            "He became quiet.",
            "Male"
        ],
        [
            "MR VISSER",
            "Probably didn't relax, but ...",
            "Male"
        ],
        [
            "LAWRENCE GERALD WASSERMAN",
            "Well he became quiet.",
            "Male"
        ],
        [
            "MR VISSER",
            "Yes.  Go on.\nMR WASSERMAN\n\"We then returned to the Nerston area.  Sikhakane stayed behind.  Col Botha drove the kombi.  I was still with Mr Cele and we drove out illegally, out of Swaziland.\"",
            "Male"
        ],
        [
            "MR VISSER",
            "Yes.\nMR WASSERMAN\n\"We then continued on to this house next to Amsterdam, where the senior officers made an attempt to - well they started to debrief him and made attempts to recruit him.\"",
            "Male"
        ],
        [
            "MR VISSER",
            "Did you take part in the interrogation or not?",
            "Male"
        ],
        [
            "LAWRENCE GERALD WASSERMAN",
            "No, I didn't.",
            "Male"
        ],
        [
            "MR VISSER",
            "Alright.  So was he willing to be recruited?",
            "Male"
        ],
        [
            "CHAIRPERSON",
            "Were you present when there was an attempt to interrogate him or recruit him?",
            "Unknown"
        ],
        [
            "LAWRENCE GERALD WASSERMAN",
            "Not.  No, Sir, not in any form.",
            "Male"
        ],
        [
            "CHAIRPERSON",
            "Yes.",
            "Unknown"
        ],
        [
            "MR VISSER",
            "Right.  Did you the at some point leave Amsterdam and go to a farm in the Elandskop area in the district of Pietermaritzburg?",
            "Male"
        ],
        [
            "LAWRENCE GERALD WASSERMAN",
            "That's correct, Sir.",
            "Male"
        ],
        [
            "MR VISSER",
            "In paragraph 10 you say after you arrived on the farm, at some point Col Botha left for Durban.",
            "Male"
        ],
        [
            "LAWRENCE GERALD WASSERMAN",
            "That is correct, Sir.",
            "Male"
        ],
        [
            "MR VISSER",
            "And he was not present during the remainder of the event?",
            "Male"
        ],
        [
            "LAWRENCE GERALD WASSERMAN",
            "Correct, Mr Chairman.",
            "Male"
        ],
        [
            "MR VISSER",
            "What happened on the farm?",
            "Male"
        ],
        [
            "LAWRENCE GERALD WASSERMAN",
            "On the farm Cols Taylor and Vorster continued in length to try and recruit Mr Cele to come over.",
            "Male"
        ],
        [
            "MR VISSER",
            "Were you present at that time from time to time?",
            "Male"
        ],
        [
            "LAWRENCE GERALD WASSERMAN",
            "From time to time, very irregularly, Mr Chair.",
            "Male"
        ],
        [
            "MR VISSER",
            "Did you gain the impression that Mr Cele was willing to co-operate?",
            "Male"
        ],
        [
            "LAWRENCE GERALD WASSERMAN",
            "I was informed by both Taylor and Vorster that he was not prepared to co-operate.",
            "Male"
        ],
        [
            "MR VISSER",
            "Please carry on with paragraph 12.\nMR WASSERMAN\n\"Much much later, Col Taylor informed me that it was virtually impossible for this man to co-operate and I then went in and I had a chat with him.  He then gave me the impression that he would not co-operate.  I slapped him three or four times.  It made no difference whatsoever.\"",
            "Male"
        ],
        [
            "MR VISSER",
            "Was this a serious assault?",
            "Male"
        ],
        [
            "LAWRENCE GERALD WASSERMAN",
            "No, it was not serious, Mr Chairman.",
            "Male"
        ],
        [
            "MR VISSER",
            "Why did you slap him?",
            "Male"
        ],
        [
            "LAWRENCE GERALD WASSERMAN",
            "Up to that stage Mr Taylor and Mr Vorster had been \"Mr Nice Guy\", in one of the techniques that we use, so I was prepared to see if the raucous shouting and few slaps would create a different environment, but it did not work.",
            "Male"
        ],
        [
            "MR VISSER",
            "Alright.  In paragraph 13 you say that Taylor then spoke to you and Vorster and stated that it's clear that Cele was not recruitable, is that correct?",
            "Male"
        ],
        [
            "LAWRENCE GERALD WASSERMAN",
            "That is correct, Mr Chairman.",
            "Male"
        ],
        [
            "MR VISSER",
            "Continue there please.\nMR WASSERMAN\n\"He gave us various reasons.  He did state that if Cele were to be released it would be an embarrassment to the South African Government, as he had been abducted illegally in Swaziland and brought out illegally to the Republic.  That was one of the major reasons.\"",
            "Male"
        ],
        [
            "MR VISSER",
            "Yes, and could Cele, according to your insight, be released to go back to Swaziland unhindered?",
            "Male"
        ],
        [
            "LAWRENCE GERALD WASSERMAN",
            "No, Mr Chairman.",
            "Male"
        ],
        [
            "MR VISSER",
            "Why not?",
            "Male"
        ],
        [
            "LAWRENCE GERALD WASSERMAN",
            "He could have - he would have continued with his activities.  In addition, placed Sikhakane in danger, as he would have realised by now that he was an agent of the Security Police.",
            "Male"
        ],
        [
            "MR VISSER",
            "Yes.  And you say in paragraph 13, Taylor then ordered Vorster and yourself to see to it that Cele be eliminated?",
            "Male"
        ],
        [
            "LAWRENCE GERALD WASSERMAN",
            "That is correct, Mr Chairman.",
            "Male"
        ],
        [
            "MR VISSER",
            "Did you associate yourself with that order?",
            "Male"
        ],
        [
            "LAWRENCE GERALD WASSERMAN",
            "Yes, I did, Mr Chairman.",
            "Male"
        ],
        [
            "MR VISSER",
            "What did you then do, you and Vorster?",
            "Male"
        ],
        [
            "LAWRENCE GERALD WASSERMAN",
            "Mr Vorster and I then proceeded to the pine tree plantation where we commenced to dig a grave.  And once we had dug that grave we returned to the house where Mr Taylor was still with Mr Cele.",
            "Male"
        ],
        [
            "MR VISSER",
            "Yes.  You remember something when you entered, is that correct?",
            "Male"
        ],
        [
            "LAWRENCE GERALD WASSERMAN",
            "Yes.  Once when we'd entered the house, Mr Taylor gave us the sign that Mr Cele was to be now taken outside and to be eliminated and I realised that Mr Cele had not - had decided not to co-operate at all.",
            "Male"
        ],
        [
            "MR VISSER",
            "And that you had to proceed.",
            "Male"
        ],
        [
            "LAWRENCE GERALD WASSERMAN",
            "And we had to proceed with the operation.",
            "Male"
        ],
        [
            "MR VISSER",
            "Yes.\nMR WASSERMAN\n\"We then informed Mr Cele that he was going to be moved to another safehouse.  We blindfolded him so he could not see where he could go.  His hands were handcuffed behind his back.\"",
            "Male"
        ],
        [
            "MR VISSER",
            "Now the blindfold you're talking about, Mr Vorster seems to remember a hood made of material of some kind.  What is your recollection, if anything, about the blindfold?",
            "Male"
        ],
        [
            "LAWRENCE GERALD WASSERMAN",
            "I can't recall if it was a bag or if it was merely a piece of cloth wrapped around the eyes, Mr Chairman.",
            "Male"
        ],
        [
            "MR VISSER",
            "Alright.  What did you do then?\nMR WASSERMAN\n\"His hands were cuffed behind his back and we took him outside, outside the house and off the veranda and along the road, he walked along the road to the graveside.\"",
            "Male"
        ],
        [
            "MR VISSER",
            "Did you steer him in the direction which you wanted him to go?",
            "Male"
        ],
        [
            "LAWRENCE GERALD WASSERMAN",
            "That's correct, Mr Chairman.",
            "Male"
        ],
        [
            "MR VISSER",
            "Yes.\nMR WASSERMAN\n\"At the spot right next to the grave I had in my possession a police baton.  I rendered him unconscious with a heavy blow to the head.\"",
            "Male"
        ],
        [
            "MR VISSER",
            "Why did you do that?",
            "Male"
        ],
        [
            "LAWRENCE GERALD WASSERMAN",
            "To render him unconscious, Mr Chairman.",
            "Male"
        ],
        [
            "MR VISSER",
            "For what purpose?",
            "Male"
        ],
        [
            "LAWRENCE GERALD WASSERMAN",
            "Then I was able to shoot.  So he would not know.",
            "Male"
        ],
        [
            "MR VISSER",
            "Alright.  Please continue.\nMR WASSERMAN\n\"Once unconscious I shot Mr Cele twice in the head.\"",
            "Male"
        ],
        [
            "MR VISSER",
            "What with?",
            "Male"
        ],
        [
            "LAWRENCE GERALD WASSERMAN",
            "With a silenced makarov.",
            "Male"
        ],
        [
            "MR VISSER",
            "Was this your firearm?",
            "Male"
        ],
        [
            "LAWRENCE GERALD WASSERMAN",
            "No, this makarov had been given to me earlier by Mr Taylor.",
            "Male"
        ],
        [
            "MR VISSER",
            "Right.\nMR WASSERMAN\n\"He was then placed in the grave.\"",
            "Male"
        ],
        [
            "MR VISSER",
            "And the grave was filled in?",
            "Male"
        ],
        [
            "LAWRENCE GERALD WASSERMAN",
            "Clothing first removed.",
            "Male"
        ],
        [
            "MR VISSER",
            "I'm sorry yes, you removed his clothing.",
            "Male"
        ],
        [
            "LAWRENCE GERALD WASSERMAN",
            "Yes.",
            "Male"
        ],
        [
            "MR VISSER",
            "Can you remember whether you left any of the clothing on the body or whether you took everything off?",
            "Male"
        ],
        [
            "LAWRENCE GERALD WASSERMAN",
            "Mr Chairman, I seem to recall he was completely naked, but I could be wrong.",
            "Male"
        ],
        [
            "MR VISSER",
            "Yes, alright.  And then you filled in the grave.",
            "Male"
        ],
        [
            "LAWRENCE GERALD WASSERMAN",
            "We filled in the grave.  After sprinkling some line on the body first, Mr Chairman.",
            "Male"
        ],
        [
            "MR VISSER",
            "Yes. Do you agree with Mr Vorster as to the reasons or the purpose of the lime?",
            "Male"
        ],
        [
            "LAWRENCE GERALD WASSERMAN",
            "Yes, Mr Chairman, I do.",
            "Male"
        ],
        [
            "MR VISSER",
            "Right, and then what did you do?",
            "Male"
        ],
        [
            "LAWRENCE GERALD WASSERMAN",
            "We then filled in the grave and then proceeded up to the house with the clothing and burnt the clothing to ashes, to cinders.",
            "Male"
        ],
        [
            "MR VISSER",
            "How do you see your participation in this incident as you set it out from paragraph 19 onwards?",
            "Male"
        ],
        [
            "LAWRENCE GERALD WASSERMAN",
            "Mr Chairman, in doing what I did I saw as my duties as a policemen ...(indistinct) of the Security Branch, and I saw it as relevant to battling the conflict and the political violence that we were undergoing at the time.",
            "Male"
        ],
        [
            "MR VISSER",
            "Go on.",
            "Male"
        ],
        [
            "LAWRENCE GERALD WASSERMAN",
            "We were conditioned by speeches of politicians and directions of our senior officers, to do all that was in our power to confront the revolutionary onslaught at all costs.  And there were times when in terms of the prevailing legislation of the time, it was not possible to solve all the problems that came our way.  And the present case is perhaps an example of such an instance.\n\tIn view of the above, I was in the bona fide belief that what I did in the present instance, in order to combat or derail the revolutionary onset and to protect the government and the National Party from political embarrassment, did fall within my express or implied authorities.  \n\tI did not participate in these events for any  personal gain and was not driven by any personal spite or malice and I received no reward.",
            "Male"
        ],
        [
            "MR VISSER",
            "You apply at page 1, for amnesty for the abduction or the man stealing - I notice in the Criminal Procedure Act it's two different offences Chairperson, I wasn't aware of that.  I'm not quite certain which is the major offence, although it would appear that abduction might be because under the old Criminal Procedure code, abduction was a capital offence, you could receive the death penalty for that.  But be that as it may, you apply for abduction or man stealing of Mr Dion Cele, his unlawful detention or depravation of his liberty, his murder - yes, I've forgotten Chairperson, I do apologise - for the assault on Mr Cele as you have explained, here in Swaziland as well as on the farm and for - and what I've also neglected to put in in your case is any offence in terms of regulations pertaining to movement, border movements.  Is that correct?  As well as any offence or delict which may be supported by the fact.  Is that so?",
            "Male"
        ],
        [
            "LAWRENCE GERALD WASSERMAN",
            "That's so, Mr Chairman.",
            "Male"
        ],
        [
            "MR VISSER",
            "Thank you, Mr Chairman, that is the evidence which we wish to place before you.\nNO FURTHER QUESTIONS BY MR VISSER",
            "Male"
        ],
        [
            "CHAIRPERSON",
            "It has just occurred to me that we don't know the date on which this man was abducted.  Can you tell us when that was?",
            "Unknown"
        ],
        [
            "MR VISSER",
            "Mr Chairman, if my memory serves me well it was the 6th of July 1988.  May I just check please, Chairman.  Mr Chairman, can we check that, whether we have a specific date during the lunch hour and inform you when we come back?",
            "Male"
        ],
        [
            "CHAIRPERSON",
            "Yes, and likewise the date on which he was killed.",
            "Unknown"
        ],
        [
            "MR VISSER",
            "Yes, certainly Chairperson.",
            "Male"
        ],
        [
            "CHAIRPERSON",
            "If you know the date of one, then you'd know without difficulty ...",
            "Unknown"
        ],
        [
            "MR VISSER",
            "Yes, certainly.  We will try to establish the exact date if possible.",
            "Male"
        ],
        [
            "CHAIRPERSON",
            "And in what language was all this discussion and negotiation with Cele taking place.",
            "Unknown"
        ],
        [
            "LAWRENCE GERALD WASSERMAN",
            "Mr Chairman, when I ever spoke to him it would have been in English, but Mr Taylor spoke in Zulu.",
            "Male"
        ],
        [
            "CHAIRPERSON",
            "And did you know that his conversation or his discussion or questioning of Cele was in Zulu?",
            "Unknown"
        ],
        [
            "LAWRENCE GERALD WASSERMAN",
            "Yes, Mr Chairman.",
            "Male"
        ],
        [
            "CHAIRPERSON",
            "You didn't have the need for an interpreter.",
            "Unknown"
        ],
        [
            "LAWRENCE GERALD WASSERMAN",
            "Mr Chairman, Mr Taylor spoke Zulu fluently, it was - he would have been handling that himself.",
            "Male"
        ],
        [
            "CHAIRPERSON",
            "Have you any questions to ask of this witness?",
            "Unknown"
        ],
        [
            "MR NEL",
            "Thank you, Mr Chairman, I've got none.\nNO QUESTIONS BY MR NEL",
            "Male"
        ],
        [
            "MR VISSER",
            "Perhaps I could answer your question straight away, Chairperson, before Ms Thabethe starts.  The TRC Report, in volume 2 at page 131, places the date in July 1988.  No closer than that.  But we will still see whether we can find a closer date.",
            "Male"
        ],
        [
            "CHAIRPERSON",
            "Yes, please.",
            "Unknown"
        ],
        [
            "MR VISSER",
            "I seem to recall having read somewhere \"6th of July\", Mr Chairman.",
            "Male"
        ],
        [
            "CHAIRPERSON",
            "Yes, well you'll let us know.  Have you any questions, Ms Thabethe?",
            "Unknown"
        ],
        [
            "MS THABETHE",
            "Just a few, Mr Chair.",
            "Female"
        ],
        [
            "CHAIRPERSON",
            "Yes, please do.",
            "Unknown"
        ],
        [
            "MS THABETHE",
            "Thank you.\n\tActually, Mr Wasserman it's one question.  How do you reconcile the evidence of Mr Botha and Vorster, that at no stage was Mr Cele assaulted and your evidence that he was assaulted by yourself in Swaziland and on the farm?",
            "Female"
        ],
        [
            "LAWRENCE GERALD WASSERMAN",
            "Well I never saw either of them ever assault him.",
            "Male"
        ],
        [
            "CHAIRPERSON",
            "I think the question clearly is that it seems that they didn't see you assault him.  In other words, there was no evidence of any assault as far as they were concerned, and you\nhave told us that you assaulted.  And I think the question is now, are you in a position to reconcile the difference between your evidence and their evidence?",
            "Unknown"
        ],
        [
            "LAWRENCE GERALD WASSERMAN",
            "Oh, now I understand yes, Sir.  The assault in Swaziland, I would hardly even say that was an assault, that was a matter of first of all securing the man there.  Mr Vorster and Mr Botha weren't present in the farmhouse when I assault Dion Cele in the farmhouse.  They were not present, so they would not know, Mr Chairman.",
            "Male"
        ],
        [
            "MS THABETHE",
            "Thank you, Mr Chair, I have no further questions.\nNO FURTHER QUESTIONS BY MS THABETHE",
            "Female"
        ],
        [
            "CHAIRPERSON",
            "Thank you.",
            "Unknown"
        ],
        [
            "MR LAX",
            "Just for the sake of clarity and for the record, Mr Botha did in fact say in his testimony that he does recall you\nassaulting the deceased in the car, in the kombi when you were trying to subdue him at that point.  So just for the record, he did say that in fact.",
            "Male"
        ],
        [
            "LAWRENCE GERALD WASSERMAN",
            "Yes, Mr Chairman.",
            "Male"
        ],
        [
            "MR LAX",
            "Do you know what happened to the shell casings when you shot him?",
            "Male"
        ],
        [
            "LAWRENCE GERALD WASSERMAN",
            "Mr Chairman, he would have been in the grave, I would have leant into the grave, I would imagine the \"doppies\" would have fallen into the grave.",
            "Male"
        ],
        [
            "MR LAX",
            "But obviously you've no idea.",
            "Male"
        ],
        [
            "LAWRENCE GERALD WASSERMAN",
            "No, I have no idea.  Perhaps they were lost in the exhumation, I don't know.",
            "Male"
        ],
        [
            "CHAIRPERSON",
            "Yes.",
            "Unknown"
        ],
        [
            "ADV BOSMAN",
            "Thank you, Chairperson.\n\tMr Wasserman, just on the issue of the interrogation.  On a question put to you by the Chairman, you responded that Mr Cele was fluent in Zulu.  What interests me was were the other interrogators fluent in Zulu?  Did he speak Zulu all the time?",
            "Unknown"
        ],
        [
            "LAWRENCE GERALD WASSERMAN",
            "Mr Chairman, when I ever spoke to him he spoke to me in English.  I think when Mr Vorster and Mr Botha spoke to him he spoke in English, but when he spoke with Mr Taylor the entire proceedings would have been in Zulu, and they were in Zulu in my presence.",
            "Male"
        ],
        [
            "ADV BOSMAN",
            "Thank you.  Thank you, Chairperson.",
            "Unknown"
        ],
        [
            "CHAIRPERSON",
            "Thank you very much, you're excused.\nWITNESS EXCUSED",
            "Unknown"
        ],
        [
            "CHAIRPERSON",
            "It's the appropriate time to take the adjournment.  Mr Visser, we are going to adjourn for 45 minutes, we'll resume at a quarter to two.",
            "Unknown"
        ],
        [
            "MR NEL",
            "Mr Chairperson, I wonder if I may ask for an indulgence till 2 o'clock, I have a problem that I have to rush back to the office because police headquarters have queried me and they would like an answer from me with regards to the queries of my further appearances on behalf of Col Taylor, before 3 o'clock this afternoon.  I'm terribly sorry to put the Committee in this position, but I will be back at 2 o'clock if it is possible.",
            "Male"
        ],
        [
            "CHAIRPERSON",
            "Yes.  We will not - you understand that you'll be proceeding on behalf of Col Taylor?",
            "Unknown"
        ],
        [
            "MR NEL",
            "Mr Chairperson, the other applications, for instance the Thombi Khubeka matter, was orchestrated by Mr Taylor and in consultation with my learned colleagues here, they have felt and I have - well I have brought it to the police' attention that it might be of assistance if I do appear on his behalf.",
            "Male"
        ],
        [
            "CHAIRPERSON",
            "Well we can't deal with an application for amnesty on behalf of somebody who is deceased.",
            "Unknown"
        ],
        [
            "MR NEL",
            "I realise that.",
            "Male"
        ],
        [
            "CHAIRPERSON",
            "So I think that should eliminate that problem.",
            "Unknown"
        ],
        [
            "MR NEL",
            "Very well, Mr Chair, I'll be back at quarter to two.",
            "Male"
        ],
        [
            "CHAIRPERSON",
            "But you can try, if you can be back at quarter to, we'll resume at a quarter to two.",
            "Unknown"
        ],
        [
            "MR NEL",
            "Thank you, Sir.",
            "Male"
        ],
        [
            "CHAIRPERSON",
            "We'll adjourn.\nCOMMITTEE ADJOURNS",
            "Unknown"
        ]
    ]
}